{"aiart_index.md":"CmPzw04g","about_index.md":"D8VKTZmY","developer_git_push.md":"Dum6z6HO","developer_git_status.md":"CB3BiF67","resource_index.md":"DqN0ynZS","developer_git_blame.md":"CexFgx4z","developer_frontend_vue_index.md":"DkjBHk7R","developer_frontend_index.md":"-XlpWlcJ","developer_git_create.md":"B7zR9WE1","developer_frontend_npm_index.md":"DyxDMdaa","tools_index.md":"BxP-ZWLI","developer_git_add.md":"DiYx0970","developer_git_branch.md":"DMDo3mvX","developer_git_stash.md":"CcwZbqCo","developer_git_revert.md":"CYdFn5wo","developer_git_remoe.md":"DImOTLDv","developer_git_config.md":"D01Nu51v","developer_git_clone.md":"C5bm7bix","developer_git_log.md":"DioaVxQE","developer_git_delete.md":"BQaYjovA","developer_git_manage.md":"DmkWdaGe","developer_git_merge.md":"ChWxpfZa","developer_git_index.md":"BrKEMTD2","developer_git_init.md":"DLcp2Nrh","developer_git_commit.md":"CIca7kyq","developer_git_transfer.md":"3wzpLZ8K","developer_git_stage.md":"OS7B6F0r","developer_git_switch.md":"CKqwOfJK","developer_git_tag.md":"CHXMv5E3","developer_git_rename.md":"C8xwexrO","developer_system_centos_index.md":"DYbX-v0n","index.md":"Dl9uMvp3"}
